Metadata-Version: 2.1
Name: pyppeteer-ghost-cursor
Version: 0.2.3
Summary: Pyppeteer implementation of Xetera/ghost-cursor
Home-page: https://github.com/mcolella14/pyppeteer_ghost_cursor
Author: mcolella14
Author-email: mcolella14@gmail.com
License: MIT
Platform: UNKNOWN
Classifier: Development Status :: 7 - Inactive
Classifier: Topic :: Software Development :: Testing
Classifier: Topic :: Internet :: WWW/HTTP :: Browsers
Classifier: Intended Audience :: Developers
Classifier: Programming Language :: Python :: 3
Classifier: Programming Language :: Python :: 3.7
Classifier: Programming Language :: Python :: 3.8
Classifier: Programming Language :: Python :: 3.9
Classifier: License :: OSI Approved :: MIT License
Classifier: Operating System :: OS Independent
Requires-Dist: bezier
